[{"url": "https://tracker-vaults.makerdao.network/data/main", "method": "GET", "payload": "", "status_code": 200, "response": "{\n  \"status\": \"success\", \n  \"data\": {\n    \"total_debt\": \"5,281,904,941.02\", \n    \"collaterals\": [\n      {\n        \"ACTIVE_VAULTS\": \"1\", \n        \"AVAILABLE_COLLATERAL\": \"0.00\", \n        \"AVAILABLE_DEBT\": \"0.00\", \n        \"COLLATERAL\": \"<a title=Vaults using PSM-USDC-A href=\\\"/collateral/PSM-USDC-A\\\">PSM-USDC-A</a>\", \n        \"COLLATERALIZATION\": \"100.00%\", \n        \"LOCKED_VALUE\": \"2,775,164,912.25\", \n        \"TOTAL_DEBT\": \"2,775,164,912.25\", \n        \"TOTAL_VAULTS\": \"1\"\n      }, \n      {\n        \"ACTIVE_VAULTS\": \"1\", \n        \"AVAILABLE_COLLATERAL\": \"-499,950,317.23\", \n        \"AVAILABLE_DEBT\": \"-499,950,317.23\", \n        \"COLLATERAL\": \"<a title=Vaults using RWA007-A href=\\\"/collateral/RWA007-A\\\">RWA007-A</a>\", \n        \"COLLATERALIZATION\": \"0.00%\", \n        \"LOCKED_VALUE\": \"1.00\", \n        \"TOTAL_DEBT\": \"499,950,318.23\", \n        \"TOTAL_VAULTS\": \"1\"\n      }, \n      {\n        \"ACTIVE_VAULTS\": \"1\", \n        \"AVAILABLE_COLLATERAL\": \"0.00\", \n        \"AVAILABLE_DEBT\": \"0.00\", \n        \"COLLATERAL\": \"<a title=Vaults using PSM-GUSD-A href=\\\"/collateral/PSM-GUSD-A\\\">PSM-GUSD-A</a>\", \n        \"COLLATERALIZATION\": \"100.00%\", \n        \"LOCKED_VALUE\": \"306,975,598.26\", \n        \"TOTAL_DEBT\": \"306,975,598.26\", \n        \"TOTAL_VAULTS\": \"1\"\n      }, \n      {\n        \"ACTIVE_VAULTS\": \"370\", \n        \"AVAILABLE_COLLATERAL\": \"435,716.18\", \n        \"AVAILABLE_DEBT\": \"476,955,440.27\", \n        \"COLLATERAL\": \"<a title=Vaults using ETH-C href=\\\"/collateral/ETH-C\\\">ETH-C</a>\", \n        \"COLLATERALIZATION\": \"443.94%\", \n        \"LOCKED_VALUE\": \"1,314,004,628.19\", \n        \"TOTAL_DEBT\": \"295,988,458.67\", \n        \"TOTAL_VAULTS\": \"1,849\"\n      }, \n      {\n        \"ACTIVE_VAULTS\": \"1\", \n        \"AVAILABLE_COLLATERAL\": \"0.00\", \n        \"AVAILABLE_DEBT\": \"0.00\", \n        \"COLLATERAL\": \"<a title=Vaults using PSM-PAX-A href=\\\"/collateral/PSM-PAX-A\\\">PSM-PAX-A</a>\", \n        \"COLLATERALIZATION\": \"100.00%\", \n        \"LOCKED_VALUE\": \"281,818,111.70\", \n        \"TOTAL_DEBT\": \"281,818,111.70\", \n        \"TOTAL_VAULTS\": \"1\"\n      }, \n      {\n        \"ACTIVE_VAULTS\": \"1,077\", \n        \"AVAILABLE_COLLATERAL\": \"345,884.80\", \n        \"AVAILABLE_DEBT\": \"443,901,397.61\", \n        \"COLLATERAL\": \"<a title=Vaults using ETH-A href=\\\"/collateral/ETH-A\\\">ETH-A</a>\", \n        \"COLLATERALIZATION\": \"425.18%\", \n        \"LOCKED_VALUE\": \"976,768,855.53\", \n        \"TOTAL_DEBT\": \"229,732,295.86\", \n        \"TOTAL_VAULTS\": \"19,141\"\n      }, \n      {\n        \"ACTIVE_VAULTS\": \"83\", \n        \"AVAILABLE_COLLATERAL\": \"267,538.14\", \n        \"AVAILABLE_DEBT\": \"350,726,267.33\", \n        \"COLLATERAL\": \"<a title=Vaults using WSTETH-A href=\\\"/collateral/WSTETH-A\\\">WSTETH-A</a>\", \n        \"COLLATERALIZATION\": \"504.19%\", \n        \"LOCKED_VALUE\": \"822,022,886.47\", \n        \"TOTAL_DEBT\": \"163,038,036.71\", \n        \"TOTAL_VAULTS\": \"426\"\n      }, \n      {\n        \"ACTIVE_VAULTS\": \"36\", \n        \"AVAILABLE_COLLATERAL\": \"2,074.55\", \n        \"AVAILABLE_DEBT\": \"411,998.76\", \n        \"COLLATERAL\": \"<a title=Vaults using GUNIV3DAIUSDC2-A href=\\\"/collateral/GUNIV3DAIUSDC2-A\\\">GUNIV3DAIUSDC2-A</a>\", \n        \"COLLATERALIZATION\": \"102.40%\", \n        \"LOCKED_VALUE\": \"106,644,296.71\", \n        \"TOTAL_DEBT\": \"104,141,233.30\", \n        \"TOTAL_VAULTS\": \"264\"\n      }, \n      {\n        \"ACTIVE_VAULTS\": \"136\", \n        \"AVAILABLE_COLLATERAL\": \"187,586.76\", \n        \"AVAILABLE_DEBT\": \"212,683,120.40\", \n        \"COLLATERAL\": \"<a title=Vaults using WSTETH-B href=\\\"/collateral/WSTETH-B\\\">WSTETH-B</a>\", \n        \"COLLATERALIZATION\": \"569.93%\", \n        \"LOCKED_VALUE\": \"582,564,037.41\", \n        \"TOTAL_DEBT\": \"102,216,359.28\", \n        \"TOTAL_VAULTS\": \"277\"\n      }, \n      {\n        \"ACTIVE_VAULTS\": \"1\", \n        \"AVAILABLE_COLLATERAL\": \"-99,999,999.00\", \n        \"AVAILABLE_DEBT\": \"-99,999,999.00\", \n        \"COLLATERAL\": \"<a title=Vaults using RWA009-A href=\\\"/collateral/RWA009-A\\\">RWA009-A</a>\", \n        \"COLLATERALIZATION\": \"0.00%\", \n        \"LOCKED_VALUE\": \"1.00\", \n        \"TOTAL_DEBT\": \"100,000,000.00\", \n        \"TOTAL_VAULTS\": \"1\"\n      }, \n      {\n        \"ACTIVE_VAULTS\": \"10\", \n        \"AVAILABLE_COLLATERAL\": \"65,302.17\", \n        \"AVAILABLE_DEBT\": \"83,821,022.64\", \n        \"COLLATERAL\": \"<a title=Vaults using CRVV1ETHSTETH-A href=\\\"/collateral/CRVV1ETHSTETH-A\\\">CRVV1ETHSTETH-A</a>\", \n        \"COLLATERALIZATION\": \"317.51%\", \n        \"LOCKED_VALUE\": \"253,837,961.03\", \n        \"TOTAL_DEBT\": \"79,945,403.83\", \n        \"TOTAL_VAULTS\": \"42\"\n      }, \n      {\n        \"ACTIVE_VAULTS\": \"1\", \n        \"AVAILABLE_COLLATERAL\": \"-69,525,267.15\", \n        \"AVAILABLE_DEBT\": \"-69,525,267.15\", \n        \"COLLATERAL\": \"<a title=Vaults using RWA013-A href=\\\"/collateral/RWA013-A\\\">RWA013-A</a>\", \n        \"COLLATERALIZATION\": \"0.00%\", \n        \"LOCKED_VALUE\": \"1.00\", \n        \"TOTAL_DEBT\": \"69,525,268.15\", \n        \"TOTAL_VAULTS\": \"1\"\n      }, \n      {\n        \"ACTIVE_VAULTS\": \"25\", \n        \"AVAILABLE_COLLATERAL\": \"269.48\", \n        \"AVAILABLE_DEBT\": \"270,251.67\", \n        \"COLLATERAL\": \"<a title=Vaults using GUNIV3DAIUSDC1-A href=\\\"/collateral/GUNIV3DAIUSDC1-A\\\">GUNIV3DAIUSDC1-A</a>\", \n        \"COLLATERALIZATION\": \"102.46%\", \n        \"LOCKED_VALUE\": \"61,313,683.00\", \n        \"TOTAL_DEBT\": \"59,841,202.25\", \n        \"TOTAL_VAULTS\": \"260\"\n      }, \n      {\n        \"ACTIVE_VAULTS\": \"81\", \n        \"AVAILABLE_COLLATERAL\": \"49,125.29\", \n        \"AVAILABLE_DEBT\": \"70,320,965.12\", \n        \"COLLATERAL\": \"<a title=Vaults using ETH-B href=\\\"/collateral/ETH-B\\\">ETH-B</a>\", \n        \"COLLATERALIZATION\": \"334.45%\", \n        \"LOCKED_VALUE\": \"149,544,997.96\", \n        \"TOTAL_DEBT\": \"44,713,648.70\", \n        \"TOTAL_VAULTS\": \"1,058\"\n      }, \n      {\n        \"ACTIVE_VAULTS\": \"129\", \n        \"AVAILABLE_COLLATERAL\": \"2,674.14\", \n        \"AVAILABLE_DEBT\": \"42,562,802.77\", \n        \"COLLATERAL\": \"<a title=Vaults using WBTC-C href=\\\"/collateral/WBTC-C\\\">WBTC-C</a>\", \n        \"COLLATERALIZATION\": \"369.62%\", \n        \"LOCKED_VALUE\": \"141,461,232.85\", \n        \"TOTAL_DEBT\": \"38,272,187.43\", \n        \"TOTAL_VAULTS\": \"346\"\n      }, \n      {\n        \"ACTIVE_VAULTS\": \"162\", \n        \"AVAILABLE_COLLATERAL\": \"2,552.22\", \n        \"AVAILABLE_DEBT\": \"49,026,908.40\", \n        \"COLLATERAL\": \"<a title=Vaults using WBTC-A href=\\\"/collateral/WBTC-A\\\">WBTC-A</a>\", \n        \"COLLATERALIZATION\": \"351.62%\", \n        \"LOCKED_VALUE\": \"120,978,025.22\", \n        \"TOTAL_DEBT\": \"34,406,212.44\", \n        \"TOTAL_VAULTS\": \"2,504\"\n      }, \n      {\n        \"ACTIVE_VAULTS\": \"13\", \n        \"AVAILABLE_COLLATERAL\": \"0.04\", \n        \"AVAILABLE_DEBT\": \"88,639.72\", \n        \"COLLATERAL\": \"<a title=Vaults using UNIV2DAIUSDC-A href=\\\"/collateral/UNIV2DAIUSDC-A\\\">UNIV2DAIUSDC-A</a>\", \n        \"COLLATERALIZATION\": \"102.38%\", \n        \"LOCKED_VALUE\": \"24,553,470.14\", \n        \"TOTAL_DEBT\": \"23,983,389.83\", \n        \"TOTAL_VAULTS\": \"79\"\n      }, \n      {\n        \"ACTIVE_VAULTS\": \"1\", \n        \"AVAILABLE_COLLATERAL\": \"-14,348,035.50\", \n        \"AVAILABLE_DEBT\": \"-14,348,035.50\", \n        \"COLLATERAL\": \"<a title=Vaults using RWA001-A href=\\\"/collateral/RWA001-A\\\">RWA001-A</a>\", \n        \"COLLATERALIZATION\": \"0.00%\", \n        \"LOCKED_VALUE\": \"1.00\", \n        \"TOTAL_DEBT\": \"14,348,036.50\", \n        \"TOTAL_VAULTS\": \"1\"\n      }, \n      {\n        \"ACTIVE_VAULTS\": \"39\", \n        \"AVAILABLE_COLLATERAL\": \"722.78\", \n        \"AVAILABLE_DEBT\": \"15,486,351.33\", \n        \"COLLATERAL\": \"<a title=Vaults using WBTC-B href=\\\"/collateral/WBTC-B\\\">WBTC-B</a>\", \n        \"COLLATERALIZATION\": \"290.80%\", \n        \"LOCKED_VALUE\": \"36,407,833.82\", \n        \"TOTAL_DEBT\": \"12,519,674.69\", \n        \"TOTAL_VAULTS\": \"128\"\n      }, \n      {\n        \"ACTIVE_VAULTS\": \"1\", \n        \"AVAILABLE_COLLATERAL\": \"-6,892,204.33\", \n        \"AVAILABLE_DEBT\": \"-6,564,004.12\", \n        \"COLLATERAL\": \"<a title=Vaults using RWA002-A href=\\\"/collateral/RWA002-A\\\">RWA002-A</a>\", \n        \"COLLATERALIZATION\": \"0.00%\", \n        \"LOCKED_VALUE\": \"1.00\", \n        \"TOTAL_DEBT\": \"6,564,005.07\", \n        \"TOTAL_VAULTS\": \"1\"\n      }, \n      {\n        \"ACTIVE_VAULTS\": \"1\", \n        \"AVAILABLE_COLLATERAL\": \"-6,825,606.95\", \n        \"AVAILABLE_DEBT\": \"-6,500,578.04\", \n        \"COLLATERAL\": \"<a title=Vaults using RWA005-A href=\\\"/collateral/RWA005-A\\\">RWA005-A</a>\", \n        \"COLLATERALIZATION\": \"0.00%\", \n        \"LOCKED_VALUE\": \"1.00\", \n        \"TOTAL_DEBT\": \"6,500,579.00\", \n        \"TOTAL_VAULTS\": \"1\"\n      }, \n      {\n        \"ACTIVE_VAULTS\": \"9\", \n        \"AVAILABLE_COLLATERAL\": \"3,371.53\", \n        \"AVAILABLE_DEBT\": \"17,348,823.50\", \n        \"COLLATERAL\": \"<a title=Vaults using YFI-A href=\\\"/collateral/YFI-A\\\">YFI-A</a>\", \n        \"COLLATERALIZATION\": \"959.42%\", \n        \"LOCKED_VALUE\": \"34,571,043.51\", \n        \"TOTAL_DEBT\": \"3,603,324.08\", \n        \"TOTAL_VAULTS\": \"320\"\n      }, \n      {\n        \"ACTIVE_VAULTS\": \"1\", \n        \"AVAILABLE_COLLATERAL\": \"-3,566,281.53\", \n        \"AVAILABLE_DEBT\": \"-3,566,281.53\", \n        \"COLLATERAL\": \"<a title=Vaults using RWA012-A href=\\\"/collateral/RWA012-A\\\">RWA012-A</a>\", \n        \"COLLATERALIZATION\": \"0.00%\", \n        \"LOCKED_VALUE\": \"1.00\", \n        \"TOTAL_DEBT\": \"3,566,282.53\", \n        \"TOTAL_VAULTS\": \"1\"\n      }, \n      {\n        \"ACTIVE_VAULTS\": \"1\", \n        \"AVAILABLE_COLLATERAL\": \"319,503.05\", \n        \"AVAILABLE_DEBT\": \"10,480,686.87\", \n        \"COLLATERAL\": \"<a title=Vaults using GNO-A href=\\\"/collateral/GNO-A\\\">GNO-A</a>\", \n        \"COLLATERALIZATION\": \"1,565.54%\", \n        \"LOCKED_VALUE\": \"47,244,648.81\", \n        \"TOTAL_DEBT\": \"3,017,784.22\", \n        \"TOTAL_VAULTS\": \"1\"\n      }, \n      {\n        \"ACTIVE_VAULTS\": \"25\", \n        \"AVAILABLE_COLLATERAL\": \"3,025.53\", \n        \"AVAILABLE_DEBT\": \"3,561,826.77\", \n        \"COLLATERAL\": \"<a title=Vaults using RETH-A href=\\\"/collateral/RETH-A\\\">RETH-A</a>\", \n        \"COLLATERALIZATION\": \"398.33%\", \n        \"LOCKED_VALUE\": \"10,563,317.52\", \n        \"TOTAL_DEBT\": \"2,651,889.41\", \n        \"TOTAL_VAULTS\": \"47\"\n      }, \n      {\n        \"ACTIVE_VAULTS\": \"5\", \n        \"AVAILABLE_COLLATERAL\": \"0.03\", \n        \"AVAILABLE_DEBT\": \"5,032,638.18\", \n        \"COLLATERAL\": \"<a title=Vaults using UNIV2USDCETH-A href=\\\"/collateral/UNIV2USDCETH-A\\\">UNIV2USDCETH-A</a>\", \n        \"COLLATERALIZATION\": \"394.47%\", \n        \"LOCKED_VALUE\": \"8,679,523.73\", \n        \"TOTAL_DEBT\": \"2,200,298.27\", \n        \"TOTAL_VAULTS\": \"105\"\n      }, \n      {\n        \"ACTIVE_VAULTS\": \"27\", \n        \"AVAILABLE_COLLATERAL\": \"253,161.28\", \n        \"AVAILABLE_DEBT\": \"1,116,422.25\", \n        \"COLLATERAL\": \"<a title=Vaults using LINK-A href=\\\"/collateral/LINK-A\\\">LINK-A</a>\", \n        \"COLLATERALIZATION\": \"287.19%\", \n        \"LOCKED_VALUE\": \"4,329,552.83\", \n        \"TOTAL_DEBT\": \"1,507,549.16\", \n        \"TOTAL_VAULTS\": \"530\"\n      }, \n      {\n        \"ACTIVE_VAULTS\": \"1\", \n        \"AVAILABLE_COLLATERAL\": \"-1,429,762.98\", \n        \"AVAILABLE_DEBT\": \"-1,299,784.52\", \n        \"COLLATERAL\": \"<a title=Vaults using RWA004-A href=\\\"/collateral/RWA004-A\\\">RWA004-A</a>\", \n        \"COLLATERALIZATION\": \"0.00%\", \n        \"LOCKED_VALUE\": \"1.00\", \n        \"TOTAL_DEBT\": \"1,299,785.43\", \n        \"TOTAL_VAULTS\": \"1\"\n      }, \n      {\n        \"ACTIVE_VAULTS\": \"1\", \n        \"AVAILABLE_COLLATERAL\": \"-1,137,458.25\", \n        \"AVAILABLE_DEBT\": \"-1,083,293.57\", \n        \"COLLATERAL\": \"<a title=Vaults using RWA003-A href=\\\"/collateral/RWA003-A\\\">RWA003-A</a>\", \n        \"COLLATERALIZATION\": \"0.00%\", \n        \"LOCKED_VALUE\": \"1.00\", \n        \"TOTAL_DEBT\": \"1,083,294.53\", \n        \"TOTAL_VAULTS\": \"1\"\n      }, \n      {\n        \"ACTIVE_VAULTS\": \"3\", \n        \"AVAILABLE_COLLATERAL\": \"649,060.54\", \n        \"AVAILABLE_DEBT\": \"418,486.82\", \n        \"COLLATERAL\": \"<a title=Vaults using MATIC-A href=\\\"/collateral/MATIC-A\\\">MATIC-A</a>\", \n        \"COLLATERALIZATION\": \"321.72%\", \n        \"LOCKED_VALUE\": \"1,605,844.49\", \n        \"TOTAL_DEBT\": \"499,138.60\", \n        \"TOTAL_VAULTS\": \"35\"\n      }, \n      {\n        \"ACTIVE_VAULTS\": \"0\", \n        \"AVAILABLE_COLLATERAL\": \"0.00\", \n        \"AVAILABLE_DEBT\": \"0.00\", \n        \"COLLATERAL\": \"<a title=Vaults using SAI href=\\\"/collateral/SAI\\\">SAI</a>\", \n        \"COLLATERALIZATION\": \"-\", \n        \"LOCKED_VALUE\": \"0.00\", \n        \"TOTAL_DEBT\": \"0.00\", \n        \"TOTAL_VAULTS\": \"1\"\n      }, \n      {\n        \"ACTIVE_VAULTS\": \"0\", \n        \"AVAILABLE_COLLATERAL\": \"9.45\", \n        \"AVAILABLE_DEBT\": \"6.30\", \n        \"COLLATERAL\": \"<a title=Vaults using TUSD-A href=\\\"/collateral/TUSD-A\\\">TUSD-A</a>\", \n        \"COLLATERALIZATION\": \"-\", \n        \"LOCKED_VALUE\": \"9.45\", \n        \"TOTAL_DEBT\": \"0.00\", \n        \"TOTAL_VAULTS\": \"64\"\n      }, \n      {\n        \"ACTIVE_VAULTS\": \"0\", \n        \"AVAILABLE_COLLATERAL\": \"420.37\", \n        \"AVAILABLE_DEBT\": \"12.52\", \n        \"COLLATERAL\": \"<a title=Vaults using KNC-A href=\\\"/collateral/KNC-A\\\">KNC-A</a>\", \n        \"COLLATERALIZATION\": \"-\", \n        \"LOCKED_VALUE\": \"625.05\", \n        \"TOTAL_DEBT\": \"0.00\", \n        \"TOTAL_VAULTS\": \"122\"\n      }, \n      {\n        \"ACTIVE_VAULTS\": \"0\", \n        \"AVAILABLE_COLLATERAL\": \"5.75\", \n        \"AVAILABLE_DEBT\": \"1.92\", \n        \"COLLATERAL\": \"<a title=Vaults using USDT-A href=\\\"/collateral/USDT-A\\\">USDT-A</a>\", \n        \"COLLATERALIZATION\": \"-\", \n        \"LOCKED_VALUE\": \"5.75\", \n        \"TOTAL_DEBT\": \"0.00\", \n        \"TOTAL_VAULTS\": \"39\"\n      }, \n      {\n        \"ACTIVE_VAULTS\": \"0\", \n        \"AVAILABLE_COLLATERAL\": \"2.79\", \n        \"AVAILABLE_DEBT\": \"0.19\", \n        \"COLLATERAL\": \"<a title=Vaults using PAXUSD-A href=\\\"/collateral/PAXUSD-A\\\">PAXUSD-A</a>\", \n        \"COLLATERALIZATION\": \"-\", \n        \"LOCKED_VALUE\": \"2.79\", \n        \"TOTAL_DEBT\": \"0.00\", \n        \"TOTAL_VAULTS\": \"34\"\n      }, \n      {\n        \"ACTIVE_VAULTS\": \"0\", \n        \"AVAILABLE_COLLATERAL\": \"15.90\", \n        \"AVAILABLE_DEBT\": \"99.03\", \n        \"COLLATERAL\": \"<a title=Vaults using COMP-A href=\\\"/collateral/COMP-A\\\">COMP-A</a>\", \n        \"COLLATERALIZATION\": \"-\", \n        \"LOCKED_VALUE\": \"1,980.66\", \n        \"TOTAL_DEBT\": \"0.00\", \n        \"TOTAL_VAULTS\": \"57\"\n      }, \n      {\n        \"ACTIVE_VAULTS\": \"0\", \n        \"AVAILABLE_COLLATERAL\": \"16,547.07\", \n        \"AVAILABLE_DEBT\": \"106.24\", \n        \"COLLATERAL\": \"<a title=Vaults using BAT-A href=\\\"/collateral/BAT-A\\\">BAT-A</a>\", \n        \"COLLATERALIZATION\": \"-\", \n        \"LOCKED_VALUE\": \"11,899.09\", \n        \"TOTAL_DEBT\": \"0.00\", \n        \"TOTAL_VAULTS\": \"753\"\n      }, \n      {\n        \"ACTIVE_VAULTS\": \"0\", \n        \"AVAILABLE_COLLATERAL\": \"462.00\", \n        \"AVAILABLE_DEBT\": \"385.00\", \n        \"COLLATERAL\": \"<a title=Vaults using USDC-B href=\\\"/collateral/USDC-B\\\">USDC-B</a>\", \n        \"COLLATERALIZATION\": \"-\", \n        \"LOCKED_VALUE\": \"462.00\", \n        \"TOTAL_DEBT\": \"0.00\", \n        \"TOTAL_VAULTS\": \"39\"\n      }, \n      {\n        \"ACTIVE_VAULTS\": \"0\", \n        \"AVAILABLE_COLLATERAL\": \"1,235.17\", \n        \"AVAILABLE_DEBT\": \"82.34\", \n        \"COLLATERAL\": \"<a title=Vaults using USDC-A href=\\\"/collateral/USDC-A\\\">USDC-A</a>\", \n        \"COLLATERALIZATION\": \"-\", \n        \"LOCKED_VALUE\": \"1,235.17\", \n        \"TOTAL_DEBT\": \"0.00\", \n        \"TOTAL_VAULTS\": \"1,311\"\n      }, \n      {\n        \"ACTIVE_VAULTS\": \"0\", \n        \"AVAILABLE_COLLATERAL\": \"43,289.52\", \n        \"AVAILABLE_DEBT\": \"395.30\", \n        \"COLLATERAL\": \"<a title=Vaults using ZRX-A href=\\\"/collateral/ZRX-A\\\">ZRX-A</a>\", \n        \"COLLATERALIZATION\": \"-\", \n        \"LOCKED_VALUE\": \"21,741.73\", \n        \"TOTAL_DEBT\": \"0.00\", \n        \"TOTAL_VAULTS\": \"97\"\n      }, \n      {\n        \"ACTIVE_VAULTS\": \"0\", \n        \"AVAILABLE_COLLATERAL\": \"216.64\", \n        \"AVAILABLE_DEBT\": \"73.75\", \n        \"COLLATERAL\": \"<a title=Vaults using MANA-A href=\\\"/collateral/MANA-A\\\">MANA-A</a>\", \n        \"COLLATERALIZATION\": \"-\", \n        \"LOCKED_VALUE\": \"129.06\", \n        \"TOTAL_DEBT\": \"0.00\", \n        \"TOTAL_VAULTS\": \"60\"\n      }, \n      {\n        \"ACTIVE_VAULTS\": \"0\", \n        \"AVAILABLE_COLLATERAL\": \"19.68\", \n        \"AVAILABLE_DEBT\": \"0.06\", \n        \"COLLATERAL\": \"<a title=Vaults using LRC-A href=\\\"/collateral/LRC-A\\\">LRC-A</a>\", \n        \"COLLATERALIZATION\": \"-\", \n        \"LOCKED_VALUE\": \"14.31\", \n        \"TOTAL_DEBT\": \"0.00\", \n        \"TOTAL_VAULTS\": \"94\"\n      }, \n      {\n        \"ACTIVE_VAULTS\": \"0\", \n        \"AVAILABLE_COLLATERAL\": \"0.00\", \n        \"AVAILABLE_DEBT\": \"0.00\", \n        \"COLLATERAL\": \"<a title=Vaults using BAL-A href=\\\"/collateral/BAL-A\\\">BAL-A</a>\", \n        \"COLLATERALIZATION\": \"-\", \n        \"LOCKED_VALUE\": \"0.00\", \n        \"TOTAL_DEBT\": \"0.00\", \n        \"TOTAL_VAULTS\": \"36\"\n      }, \n      {\n        \"ACTIVE_VAULTS\": \"0\", \n        \"AVAILABLE_COLLATERAL\": \"0.01\", \n        \"AVAILABLE_DEBT\": \"0.00\", \n        \"COLLATERAL\": \"<a title=Vaults using GUSD-A href=\\\"/collateral/GUSD-A\\\">GUSD-A</a>\", \n        \"COLLATERALIZATION\": \"-\", \n        \"LOCKED_VALUE\": \"0.01\", \n        \"TOTAL_DEBT\": \"0.00\", \n        \"TOTAL_VAULTS\": \"26\"\n      }, \n      {\n        \"ACTIVE_VAULTS\": \"0\", \n        \"AVAILABLE_COLLATERAL\": \"23,989.68\", \n        \"AVAILABLE_DEBT\": \"9,418.45\", \n        \"COLLATERAL\": \"<a title=Vaults using UNI-A href=\\\"/collateral/UNI-A\\\">UNI-A</a>\", \n        \"COLLATERALIZATION\": \"-\", \n        \"LOCKED_VALUE\": \"122,439.87\", \n        \"TOTAL_DEBT\": \"0.00\", \n        \"TOTAL_VAULTS\": \"298\"\n      }, \n      {\n        \"ACTIVE_VAULTS\": \"0\", \n        \"AVAILABLE_COLLATERAL\": \"0.47\", \n        \"AVAILABLE_DEBT\": \"263.52\", \n        \"COLLATERAL\": \"<a title=Vaults using RENBTC-A href=\\\"/collateral/RENBTC-A\\\">RENBTC-A</a>\", \n        \"COLLATERALIZATION\": \"-\", \n        \"LOCKED_VALUE\": \"13,175.93\", \n        \"TOTAL_DEBT\": \"0.00\", \n        \"TOTAL_VAULTS\": \"154\"\n      }, \n      {\n        \"ACTIVE_VAULTS\": \"0\", \n        \"AVAILABLE_COLLATERAL\": \"3,250.84\", \n        \"AVAILABLE_DEBT\": \"23,342.93\", \n        \"COLLATERAL\": \"<a title=Vaults using AAVE-A href=\\\"/collateral/AAVE-A\\\">AAVE-A</a>\", \n        \"COLLATERALIZATION\": \"-\", \n        \"LOCKED_VALUE\": \"490,201.52\", \n        \"TOTAL_DEBT\": \"0.00\", \n        \"TOTAL_VAULTS\": \"124\"\n      }, \n      {\n        \"ACTIVE_VAULTS\": \"0\", \n        \"AVAILABLE_COLLATERAL\": \"1.01\", \n        \"AVAILABLE_DEBT\": \"5.82\", \n        \"COLLATERAL\": \"<a title=Vaults using UNIV2DAIETH-A href=\\\"/collateral/UNIV2DAIETH-A\\\">UNIV2DAIETH-A</a>\", \n        \"COLLATERALIZATION\": \"-\", \n        \"LOCKED_VALUE\": \"116.40\", \n        \"TOTAL_DEBT\": \"0.00\", \n        \"TOTAL_VAULTS\": \"112\"\n      }, \n      {\n        \"ACTIVE_VAULTS\": \"0\", \n        \"AVAILABLE_COLLATERAL\": \"0.00\", \n        \"AVAILABLE_DEBT\": \"0.01\", \n        \"COLLATERAL\": \"<a title=Vaults using UNIV2WBTCETH-A href=\\\"/collateral/UNIV2WBTCETH-A\\\">UNIV2WBTCETH-A</a>\", \n        \"COLLATERALIZATION\": \"-\", \n        \"LOCKED_VALUE\": \"0.36\", \n        \"TOTAL_DEBT\": \"0.00\", \n        \"TOTAL_VAULTS\": \"45\"\n      }, \n      {\n        \"ACTIVE_VAULTS\": \"0\", \n        \"AVAILABLE_COLLATERAL\": \"0.00\", \n        \"AVAILABLE_DEBT\": \"0.00\", \n        \"COLLATERAL\": \"<a title=Vaults using UNIV2ETHUSDT-A href=\\\"/collateral/UNIV2ETHUSDT-A\\\">UNIV2ETHUSDT-A</a>\", \n        \"COLLATERALIZATION\": \"-\", \n        \"LOCKED_VALUE\": \"0.00\", \n        \"TOTAL_DEBT\": \"0.00\", \n        \"TOTAL_VAULTS\": \"24\"\n      }, \n      {\n        \"ACTIVE_VAULTS\": \"0\", \n        \"AVAILABLE_COLLATERAL\": \"0.00\", \n        \"AVAILABLE_DEBT\": \"0.00\", \n        \"COLLATERAL\": \"<a title=Vaults using UNIV2LINKETH-A href=\\\"/collateral/UNIV2LINKETH-A\\\">UNIV2LINKETH-A</a>\", \n        \"COLLATERALIZATION\": \"-\", \n        \"LOCKED_VALUE\": \"0.00\", \n        \"TOTAL_DEBT\": \"0.00\", \n        \"TOTAL_VAULTS\": \"20\"\n      }, \n      {\n        \"ACTIVE_VAULTS\": \"0\", \n        \"AVAILABLE_COLLATERAL\": \"0.02\", \n        \"AVAILABLE_DEBT\": \"3.28\", \n        \"COLLATERAL\": \"<a title=Vaults using UNIV2UNIETH-A href=\\\"/collateral/UNIV2UNIETH-A\\\">UNIV2UNIETH-A</a>\", \n        \"COLLATERALIZATION\": \"-\", \n        \"LOCKED_VALUE\": \"5.24\", \n        \"TOTAL_DEBT\": \"0.00\", \n        \"TOTAL_VAULTS\": \"43\"\n      }, \n      {\n        \"ACTIVE_VAULTS\": \"0\", \n        \"AVAILABLE_COLLATERAL\": \"0.00\", \n        \"AVAILABLE_DEBT\": \"0.00\", \n        \"COLLATERAL\": \"<a title=Vaults using UNIV2WBTCDAI-A href=\\\"/collateral/UNIV2WBTCDAI-A\\\">UNIV2WBTCDAI-A</a>\", \n        \"COLLATERALIZATION\": \"-\", \n        \"LOCKED_VALUE\": \"0.00\", \n        \"TOTAL_DEBT\": \"0.00\", \n        \"TOTAL_VAULTS\": \"17\"\n      }, \n      {\n        \"ACTIVE_VAULTS\": \"0\", \n        \"AVAILABLE_COLLATERAL\": \"0.00\", \n        \"AVAILABLE_DEBT\": \"0.00\", \n        \"COLLATERAL\": \"<a title=Vaults using UNIV2AAVEETH-A href=\\\"/collateral/UNIV2AAVEETH-A\\\">UNIV2AAVEETH-A</a>\", \n        \"COLLATERALIZATION\": \"-\", \n        \"LOCKED_VALUE\": \"0.00\", \n        \"TOTAL_DEBT\": \"0.00\", \n        \"TOTAL_VAULTS\": \"5\"\n      }, \n      {\n        \"ACTIVE_VAULTS\": \"0\", \n        \"AVAILABLE_COLLATERAL\": \"0.00\", \n        \"AVAILABLE_DEBT\": \"0.00\", \n        \"COLLATERAL\": \"<a title=Vaults using UNIV2DAIUSDT-A href=\\\"/collateral/UNIV2DAIUSDT-A\\\">UNIV2DAIUSDT-A</a>\", \n        \"COLLATERALIZATION\": \"-\", \n        \"LOCKED_VALUE\": \"0.00\", \n        \"TOTAL_DEBT\": \"0.00\", \n        \"TOTAL_VAULTS\": \"1\"\n      }, \n      {\n        \"ACTIVE_VAULTS\": \"0\", \n        \"AVAILABLE_COLLATERAL\": \"0.00\", \n        \"AVAILABLE_DEBT\": \"0.00\", \n        \"COLLATERAL\": \"<a title=Vaults using RWA006-A href=\\\"/collateral/RWA006-A\\\">RWA006-A</a>\", \n        \"COLLATERALIZATION\": \"-\", \n        \"LOCKED_VALUE\": \"0.00\", \n        \"TOTAL_DEBT\": \"0.00\", \n        \"TOTAL_VAULTS\": \"0\"\n      }, \n      {\n        \"ACTIVE_VAULTS\": \"0\", \n        \"AVAILABLE_COLLATERAL\": \"0.00\", \n        \"AVAILABLE_DEBT\": \"0.00\", \n        \"COLLATERAL\": \"<a title=Vaults using DIRECT-AAVEV2-DAI href=\\\"/collateral/DIRECT-AAVEV2-DAI\\\">DIRECT-AAVEV2-DAI</a>\", \n        \"COLLATERALIZATION\": \"-\", \n        \"LOCKED_VALUE\": \"0.00\", \n        \"TOTAL_DEBT\": \"0.00\", \n        \"TOTAL_VAULTS\": \"2\"\n      }, \n      {\n        \"ACTIVE_VAULTS\": \"0\", \n        \"AVAILABLE_COLLATERAL\": \"0.00\", \n        \"AVAILABLE_DEBT\": \"0.00\", \n        \"COLLATERAL\": \"<a title=Vaults using RWA008-A href=\\\"/collateral/RWA008-A\\\">RWA008-A</a>\", \n        \"COLLATERALIZATION\": \"-\", \n        \"LOCKED_VALUE\": \"0.00\", \n        \"TOTAL_DEBT\": \"0.00\", \n        \"TOTAL_VAULTS\": \"1\"\n      }, \n      {\n        \"ACTIVE_VAULTS\": \"0\", \n        \"AVAILABLE_COLLATERAL\": \"0.00\", \n        \"AVAILABLE_DEBT\": \"0.00\", \n        \"COLLATERAL\": \"<a title=Vaults using TELEPORT-FW-A href=\\\"/collateral/TELEPORT-FW-A\\\">TELEPORT-FW-A</a>\", \n        \"COLLATERALIZATION\": \"-\", \n        \"LOCKED_VALUE\": \"0.00\", \n        \"TOTAL_DEBT\": \"0.00\", \n        \"TOTAL_VAULTS\": \"1\"\n      }, \n      {\n        \"ACTIVE_VAULTS\": \"0\", \n        \"AVAILABLE_COLLATERAL\": \"0.00\", \n        \"AVAILABLE_DEBT\": \"0.00\", \n        \"COLLATERAL\": \"<a title=Vaults using DIRECT-COMPV2-DAI href=\\\"/collateral/DIRECT-COMPV2-DAI\\\">DIRECT-COMPV2-DAI</a>\", \n        \"COLLATERALIZATION\": \"-\", \n        \"LOCKED_VALUE\": \"0.00\", \n        \"TOTAL_DEBT\": \"0.00\", \n        \"TOTAL_VAULTS\": \"1\"\n      }, \n      {\n        \"ACTIVE_VAULTS\": \"0\", \n        \"AVAILABLE_COLLATERAL\": \"1.00\", \n        \"AVAILABLE_DEBT\": \"1.00\", \n        \"COLLATERAL\": \"<a title=Vaults using RWA011-A href=\\\"/collateral/RWA011-A\\\">RWA011-A</a>\", \n        \"COLLATERALIZATION\": \"-\", \n        \"LOCKED_VALUE\": \"1.00\", \n        \"TOTAL_DEBT\": \"0.00\", \n        \"TOTAL_VAULTS\": \"1\"\n      }, \n      {\n        \"ACTIVE_VAULTS\": \"0\", \n        \"AVAILABLE_COLLATERAL\": \"1.00\", \n        \"AVAILABLE_DEBT\": \"1.00\", \n        \"COLLATERAL\": \"<a title=Vaults using RWA010-A href=\\\"/collateral/RWA010-A\\\">RWA010-A</a>\", \n        \"COLLATERALIZATION\": \"-\", \n        \"LOCKED_VALUE\": \"1.00\", \n        \"TOTAL_DEBT\": \"0.00\", \n        \"TOTAL_VAULTS\": \"1\"\n      }\n    ], \n    \"collaterals_num\": 62, \n    \"vaults_num\": \"31,007\", \n    \"active_num\": \"2,243\", \n    \"debt_ceiling\": \"7,879,248,463\", \n    \"debt_utilization\": \"67.04%\", \n    \"available_debt\": \"1,081,410,688.40\", \n    \"available_collateral\": \"2,173,905,198.19\", \n    \"owners\": \"1\", \n    \"active_owners\": \"1\", \n    \"collateralization\": \"152.63%\", \n    \"locked_value\": \"8,061,718,516.78\", \n    \"refresh\": \"Thu, 06 Apr 2023 00:00:00 GMT\", \n    \"sin\": \"12,830,662.66\", \n    \"pie\": \"{\\\"data\\\": [{\\\"hole\\\": 0.3, \\\"hovertemplate\\\": \\\"Value locked (USD): %{value:,.2f}<extra></extra>\\\", \\\"labels\\\": [\\\"NON-STABLE\\\", \\\"STABLE\\\", \\\"STABLE\\\", \\\"NON-STABLE\\\", \\\"STABLE\\\", \\\"NON-STABLE\\\", \\\"STABLE\\\", \\\"STABLE\\\", \\\"STABLE\\\", \\\"STABLE\\\", \\\"NON-STABLE\\\", \\\"NON-STABLE\\\", \\\"STABLE\\\", \\\"STABLE\\\", \\\"NON-STABLE\\\", null, \\\"STABLE\\\", \\\"NON-STABLE\\\", \\\"STABLE\\\", \\\"STABLE\\\", \\\"STABLE\\\", \\\"NON-STABLE\\\", \\\"STABLE\\\", \\\"NON-STABLE\\\", \\\"NON-STABLE\\\", \\\"STABLE\\\", \\\"STABLE\\\", \\\"NON-STABLE\\\", \\\"NON-STABLE\\\", \\\"NON-STABLE\\\", \\\"NON-STABLE\\\", \\\"NON-STABLE\\\", \\\"NON-STABLE\\\", \\\"NON-STABLE\\\", \\\"NON-STABLE\\\", \\\"STABLE\\\", \\\"STABLE\\\", \\\"STABLE\\\", \\\"STABLE\\\", \\\"STABLE\\\", \\\"NON-STABLE\\\", \\\"NON-STABLE\\\", \\\"NON-STABLE\\\", \\\"STABLE\\\", \\\"NON-STABLE\\\", \\\"NON-STABLE\\\", \\\"NON-STABLE\\\", \\\"NON-STABLE\\\", \\\"NON-STABLE\\\", \\\"NON-STABLE\\\", \\\"NON-STABLE\\\", \\\"NON-STABLE\\\", \\\"NON-STABLE\\\", \\\"NON-STABLE\\\", \\\"NON-STABLE\\\", \\\"NON-STABLE\\\", \\\"NON-STABLE\\\", \\\"NON-STABLE\\\", \\\"NON-STABLE\\\", \\\"NON-STABLE\\\"], \\\"marker\\\": {\\\"colors\\\": [\\\"#1aab9b\\\", \\\"#dddddd\\\", \\\"#444444\\\", \\\"#f0f0f0\\\"]}, \\\"type\\\": \\\"pie\\\", \\\"values\\\": [976768855.533414, 106644296.70754397, 61313682.99569682, 1314004628.1926877, 306975598.26, 120978025.21910793, 1, 1, 1, 0, 0, 0, 1235.1669403048375, 1, 4329552.826621574, 0, 1, 24553470.13660895, 281818111.6967735, 1, 1, 11899.086842603427, 462, 21741.72814447808, 129.06315187891744, 2.7939959337120115, 9.453071352997192, 34571043.506037965, 5.852505766465913e-09, 13175.93198918517, 116.39678146473987, 2.301901966874382e-10, 0, 0, 149544997.9593218, 1, 2775164912.24531, 1, 1, 1, 625.0457184613381, 5.751313, 1980.6636922500743, 0.01, 122439.86613182243, 490201.5214007976, 0.35897647792123827, 8679523.729636576, 5.243171058943, 0, 0, 1605844.4861591847, 822022886.4674455, 36407833.82428271, 141461232.84884107, 253837961.03051656, 582564037.4097862, 47244648.80525529, 14.30564299454414, 10563317.51578345]}], \\\"layout\\\": {\\\"hovermode\\\": \\\"x unified\\\", \\\"template\\\": {\\\"data\\\": {\\\"bar\\\": [{\\\"error_x\\\": {\\\"color\\\": \\\"#2a3f5f\\\"}, \\\"error_y\\\": {\\\"color\\\": \\\"#2a3f5f\\\"}, \\\"marker\\\": {\\\"line\\\": {\\\"color\\\": \\\"#E5ECF6\\\", \\\"width\\\": 0.5}}, \\\"type\\\": \\\"bar\\\"}], \\\"barpolar\\\": [{\\\"marker\\\": {\\\"line\\\": {\\\"color\\\": \\\"#E5ECF6\\\", \\\"width\\\": 0.5}}, \\\"type\\\": \\\"barpolar\\\"}], \\\"carpet\\\": [{\\\"aaxis\\\": {\\\"endlinecolor\\\": \\\"#2a3f5f\\\", \\\"gridcolor\\\": \\\"white\\\", \\\"linecolor\\\": \\\"white\\\", \\\"minorgridcolor\\\": \\\"white\\\", \\\"startlinecolor\\\": \\\"#2a3f5f\\\"}, \\\"baxis\\\": {\\\"endlinecolor\\\": \\\"#2a3f5f\\\", \\\"gridcolor\\\": \\\"white\\\", \\\"linecolor\\\": \\\"white\\\", \\\"minorgridcolor\\\": \\\"white\\\", \\\"startlinecolor\\\": \\\"#2a3f5f\\\"}, \\\"type\\\": \\\"carpet\\\"}], \\\"choropleth\\\": [{\\\"colorbar\\\": {\\\"outlinewidth\\\": 0, \\\"ticks\\\": \\\"\\\"}, \\\"type\\\": \\\"choropleth\\\"}], \\\"contour\\\": [{\\\"colorbar\\\": {\\\"outlinewidth\\\": 0, \\\"ticks\\\": \\\"\\\"}, \\\"colorscale\\\": [[0, \\\"#0d0887\\\"], [0.1111111111111111, \\\"#46039f\\\"], [0.2222222222222222, \\\"#7201a8\\\"], [0.3333333333333333, \\\"#9c179e\\\"], [0.4444444444444444, \\\"#bd3786\\\"], [0.5555555555555556, \\\"#d8576b\\\"], [0.6666666666666666, \\\"#ed7953\\\"], [0.7777777777777778, \\\"#fb9f3a\\\"], [0.8888888888888888, \\\"#fdca26\\\"], [1, \\\"#f0f921\\\"]], \\\"type\\\": \\\"contour\\\"}], \\\"contourcarpet\\\": [{\\\"colorbar\\\": {\\\"outlinewidth\\\": 0, \\\"ticks\\\": \\\"\\\"}, \\\"type\\\": \\\"contourcarpet\\\"}], \\\"heatmap\\\": [{\\\"colorbar\\\": {\\\"outlinewidth\\\": 0, \\\"ticks\\\": \\\"\\\"}, \\\"colorscale\\\": [[0, \\\"#0d0887\\\"], [0.1111111111111111, \\\"#46039f\\\"], [0.2222222222222222, \\\"#7201a8\\\"], [0.3333333333333333, \\\"#9c179e\\\"], [0.4444444444444444, \\\"#bd3786\\\"], [0.5555555555555556, \\\"#d8576b\\\"], [0.6666666666666666, \\\"#ed7953\\\"], [0.7777777777777778, \\\"#fb9f3a\\\"], [0.8888888888888888, \\\"#fdca26\\\"], [1, \\\"#f0f921\\\"]], \\\"type\\\": \\\"heatmap\\\"}], \\\"heatmapgl\\\": [{\\\"colorbar\\\": {\\\"outlinewidth\\\": 0, \\\"ticks\\\": \\\"\\\"}, \\\"colorscale\\\": [[0, \\\"#0d0887\\\"], [0.1111111111111111, \\\"#46039f\\\"], [0.2222222222222222, \\\"#7201a8\\\"], [0.3333333333333333, \\\"#9c179e\\\"], [0.4444444444444444, \\\"#bd3786\\\"], [0.5555555555555556, \\\"#d8576b\\\"], [0.6666666666666666, \\\"#ed7953\\\"], [0.7777777777777778, \\\"#fb9f3a\\\"], [0.8888888888888888, \\\"#fdca26\\\"], [1, \\\"#f0f921\\\"]], \\\"type\\\": \\\"heatmapgl\\\"}], \\\"histogram\\\": [{\\\"marker\\\": {\\\"colorbar\\\": {\\\"outlinewidth\\\": 0, \\\"ticks\\\": \\\"\\\"}}, \\\"type\\\": \\\"histogram\\\"}], \\\"histogram2d\\\": [{\\\"colorbar\\\": {\\\"outlinewidth\\\": 0, \\\"ticks\\\": \\\"\\\"}, \\\"colorscale\\\": [[0, \\\"#0d0887\\\"], [0.1111111111111111, \\\"#46039f\\\"], [0.2222222222222222, \\\"#7201a8\\\"], [0.3333333333333333, \\\"#9c179e\\\"], [0.4444444444444444, \\\"#bd3786\\\"], [0.5555555555555556, \\\"#d8576b\\\"], [0.6666666666666666, \\\"#ed7953\\\"], [0.7777777777777778, \\\"#fb9f3a\\\"], [0.8888888888888888, \\\"#fdca26\\\"], [1, \\\"#f0f921\\\"]], \\\"type\\\": \\\"histogram2d\\\"}], \\\"histogram2dcontour\\\": [{\\\"colorbar\\\": {\\\"outlinewidth\\\": 0, \\\"ticks\\\": \\\"\\\"}, \\\"colorscale\\\": [[0, \\\"#0d0887\\\"], [0.1111111111111111, \\\"#46039f\\\"], [0.2222222222222222, \\\"#7201a8\\\"], [0.3333333333333333, \\\"#9c179e\\\"], [0.4444444444444444, \\\"#bd3786\\\"], [0.5555555555555556, \\\"#d8576b\\\"], [0.6666666666666666, \\\"#ed7953\\\"], [0.7777777777777778, \\\"#fb9f3a\\\"], [0.8888888888888888, \\\"#fdca26\\\"], [1, \\\"#f0f921\\\"]], \\\"type\\\": \\\"histogram2dcontour\\\"}], \\\"mesh3d\\\": [{\\\"colorbar\\\": {\\\"outlinewidth\\\": 0, \\\"ticks\\\": \\\"\\\"}, \\\"type\\\": \\\"mesh3d\\\"}], \\\"parcoords\\\": [{\\\"line\\\": {\\\"colorbar\\\": {\\\"outlinewidth\\\": 0, \\\"ticks\\\": \\\"\\\"}}, \\\"type\\\": \\\"parcoords\\\"}], \\\"pie\\\": [{\\\"automargin\\\": true, \\\"type\\\": \\\"pie\\\"}], \\\"scatter\\\": [{\\\"marker\\\": {\\\"colorbar\\\": {\\\"outlinewidth\\\": 0, \\\"ticks\\\": \\\"\\\"}}, \\\"type\\\": \\\"scatter\\\"}], \\\"scatter3d\\\": [{\\\"line\\\": {\\\"colorbar\\\": {\\\"outlinewidth\\\": 0, \\\"ticks\\\": \\\"\\\"}}, \\\"marker\\\": {\\\"colorbar\\\": {\\\"outlinewidth\\\": 0, \\\"ticks\\\": \\\"\\\"}}, \\\"type\\\": \\\"scatter3d\\\"}], \\\"scattercarpet\\\": [{\\\"marker\\\": {\\\"colorbar\\\": {\\\"outlinewidth\\\": 0, \\\"ticks\\\": \\\"\\\"}}, \\\"type\\\": \\\"scattercarpet\\\"}], \\\"scattergeo\\\": [{\\\"marker\\\": {\\\"colorbar\\\": {\\\"outlinewidth\\\": 0, \\\"ticks\\\": \\\"\\\"}}, \\\"type\\\": \\\"scattergeo\\\"}], \\\"scattergl\\\": [{\\\"marker\\\": {\\\"colorbar\\\": {\\\"outlinewidth\\\": 0, \\\"ticks\\\": \\\"\\\"}}, \\\"type\\\": \\\"scattergl\\\"}], \\\"scattermapbox\\\": [{\\\"marker\\\": {\\\"colorbar\\\": {\\\"outlinewidth\\\": 0, \\\"ticks\\\": \\\"\\\"}}, \\\"type\\\": \\\"scattermapbox\\\"}], \\\"scatterpolar\\\": [{\\\"marker\\\": {\\\"colorbar\\\": {\\\"outlinewidth\\\": 0, \\\"ticks\\\": \\\"\\\"}}, \\\"type\\\": \\\"scatterpolar\\\"}], \\\"scatterpolargl\\\": [{\\\"marker\\\": {\\\"colorbar\\\": {\\\"outlinewidth\\\": 0, \\\"ticks\\\": \\\"\\\"}}, \\\"type\\\": \\\"scatterpolargl\\\"}], \\\"scatterternary\\\": [{\\\"marker\\\": {\\\"colorbar\\\": {\\\"outlinewidth\\\": 0, \\\"ticks\\\": \\\"\\\"}}, \\\"type\\\": \\\"scatterternary\\\"}], \\\"surface\\\": [{\\\"colorbar\\\": {\\\"outlinewidth\\\": 0, \\\"ticks\\\": \\\"\\\"}, \\\"colorscale\\\": [[0, \\\"#0d0887\\\"], [0.1111111111111111, \\\"#46039f\\\"], [0.2222222222222222, \\\"#7201a8\\\"], [0.3333333333333333, \\\"#9c179e\\\"], [0.4444444444444444, \\\"#bd3786\\\"], [0.5555555555555556, \\\"#d8576b\\\"], [0.6666666666666666, \\\"#ed7953\\\"], [0.7777777777777778, \\\"#fb9f3a\\\"], [0.8888888888888888, \\\"#fdca26\\\"], [1, \\\"#f0f921\\\"]], \\\"type\\\": \\\"surface\\\"}], \\\"table\\\": [{\\\"cells\\\": {\\\"fill\\\": {\\\"color\\\": \\\"#EBF0F8\\\"}, \\\"line\\\": {\\\"color\\\": \\\"white\\\"}}, \\\"header\\\": {\\\"fill\\\": {\\\"color\\\": \\\"#C8D4E3\\\"}, \\\"line\\\": {\\\"color\\\": \\\"white\\\"}}, \\\"type\\\": \\\"table\\\"}]}, \\\"layout\\\": {\\\"annotationdefaults\\\": {\\\"arrowcolor\\\": \\\"#2a3f5f\\\", \\\"arrowhead\\\": 0, \\\"arrowwidth\\\": 1}, \\\"coloraxis\\\": {\\\"colorbar\\\": {\\\"outlinewidth\\\": 0, \\\"ticks\\\": \\\"\\\"}}, \\\"colorscale\\\": {\\\"diverging\\\": [[0, \\\"#8e0152\\\"], [0.1, \\\"#c51b7d\\\"], [0.2, \\\"#de77ae\\\"], [0.3, \\\"#f1b6da\\\"], [0.4, \\\"#fde0ef\\\"], [0.5, \\\"#f7f7f7\\\"], [0.6, \\\"#e6f5d0\\\"], [0.7, \\\"#b8e186\\\"], [0.8, \\\"#7fbc41\\\"], [0.9, \\\"#4d9221\\\"], [1, \\\"#276419\\\"]], \\\"sequential\\\": [[0, \\\"#0d0887\\\"], [0.1111111111111111, \\\"#46039f\\\"], [0.2222222222222222, \\\"#7201a8\\\"], [0.3333333333333333, \\\"#9c179e\\\"], [0.4444444444444444, \\\"#bd3786\\\"], [0.5555555555555556, \\\"#d8576b\\\"], [0.6666666666666666, \\\"#ed7953\\\"], [0.7777777777777778, \\\"#fb9f3a\\\"], [0.8888888888888888, \\\"#fdca26\\\"], [1, \\\"#f0f921\\\"]], \\\"sequentialminus\\\": [[0, \\\"#0d0887\\\"], [0.1111111111111111, \\\"#46039f\\\"], [0.2222222222222222, \\\"#7201a8\\\"], [0.3333333333333333, \\\"#9c179e\\\"], [0.4444444444444444, \\\"#bd3786\\\"], [0.5555555555555556, \\\"#d8576b\\\"], [0.6666666666666666, \\\"#ed7953\\\"], [0.7777777777777778, \\\"#fb9f3a\\\"], [0.8888888888888888, \\\"#fdca26\\\"], [1, \\\"#f0f921\\\"]]}, \\\"colorway\\\": [\\\"#636efa\\\", \\\"#EF553B\\\", \\\"#00cc96\\\", \\\"#ab63fa\\\", \\\"#FFA15A\\\", \\\"#19d3f3\\\", \\\"#FF6692\\\", \\\"#B6E880\\\", \\\"#FF97FF\\\", \\\"#FECB52\\\"], \\\"font\\\": {\\\"color\\\": \\\"#2a3f5f\\\"}, \\\"geo\\\": {\\\"bgcolor\\\": \\\"white\\\", \\\"lakecolor\\\": \\\"white\\\", \\\"landcolor\\\": \\\"#E5ECF6\\\", \\\"showlakes\\\": true, \\\"showland\\\": true, \\\"subunitcolor\\\": \\\"white\\\"}, \\\"hoverlabel\\\": {\\\"align\\\": \\\"left\\\"}, \\\"hovermode\\\": \\\"closest\\\", \\\"mapbox\\\": {\\\"style\\\": \\\"light\\\"}, \\\"paper_bgcolor\\\": \\\"white\\\", \\\"plot_bgcolor\\\": \\\"#E5ECF6\\\", \\\"polar\\\": {\\\"angularaxis\\\": {\\\"gridcolor\\\": \\\"white\\\", \\\"linecolor\\\": \\\"white\\\", \\\"ticks\\\": \\\"\\\"}, \\\"bgcolor\\\": \\\"#E5ECF6\\\", \\\"radialaxis\\\": {\\\"gridcolor\\\": \\\"white\\\", \\\"linecolor\\\": \\\"white\\\", \\\"ticks\\\": \\\"\\\"}}, \\\"scene\\\": {\\\"xaxis\\\": {\\\"backgroundcolor\\\": \\\"#E5ECF6\\\", \\\"gridcolor\\\": \\\"white\\\", \\\"gridwidth\\\": 2, \\\"linecolor\\\": \\\"white\\\", \\\"showbackground\\\": true, \\\"ticks\\\": \\\"\\\", \\\"zerolinecolor\\\": \\\"white\\\"}, \\\"yaxis\\\": {\\\"backgroundcolor\\\": \\\"#E5ECF6\\\", \\\"gridcolor\\\": \\\"white\\\", \\\"gridwidth\\\": 2, \\\"linecolor\\\": \\\"white\\\", \\\"showbackground\\\": true, \\\"ticks\\\": \\\"\\\", \\\"zerolinecolor\\\": \\\"white\\\"}, \\\"zaxis\\\": {\\\"backgroundcolor\\\": \\\"#E5ECF6\\\", \\\"gridcolor\\\": \\\"white\\\", \\\"gridwidth\\\": 2, \\\"linecolor\\\": \\\"white\\\", \\\"showbackground\\\": true, \\\"ticks\\\": \\\"\\\", \\\"zerolinecolor\\\": \\\"white\\\"}}, \\\"shapedefaults\\\": {\\\"line\\\": {\\\"color\\\": \\\"#2a3f5f\\\"}}, \\\"ternary\\\": {\\\"aaxis\\\": {\\\"gridcolor\\\": \\\"white\\\", \\\"linecolor\\\": \\\"white\\\", \\\"ticks\\\": \\\"\\\"}, \\\"baxis\\\": {\\\"gridcolor\\\": \\\"white\\\", \\\"linecolor\\\": \\\"white\\\", \\\"ticks\\\": \\\"\\\"}, \\\"bgcolor\\\": \\\"#E5ECF6\\\", \\\"caxis\\\": {\\\"gridcolor\\\": \\\"white\\\", \\\"linecolor\\\": \\\"white\\\", \\\"ticks\\\": \\\"\\\"}}, \\\"title\\\": {\\\"x\\\": 0.05}, \\\"xaxis\\\": {\\\"automargin\\\": true, \\\"gridcolor\\\": \\\"white\\\", \\\"linecolor\\\": \\\"white\\\", \\\"ticks\\\": \\\"\\\", \\\"title\\\": {\\\"standoff\\\": 15}, \\\"zerolinecolor\\\": \\\"white\\\", \\\"zerolinewidth\\\": 2}, \\\"yaxis\\\": {\\\"automargin\\\": true, \\\"gridcolor\\\": \\\"white\\\", \\\"linecolor\\\": \\\"white\\\", \\\"ticks\\\": \\\"\\\", \\\"title\\\": {\\\"standoff\\\": 15}, \\\"zerolinecolor\\\": \\\"white\\\", \\\"zerolinewidth\\\": 2}}}}}\", \n    \"bar\": \"{\\\"data\\\": [{\\\"hovertemplate\\\": \\\"%{y:,.2f}<extra></extra>\\\", \\\"marker\\\": {\\\"color\\\": \\\"#dddddd\\\"}, \\\"name\\\": \\\"Value locked (USD)\\\", \\\"type\\\": \\\"bar\\\", \\\"x\\\": [\\\"REGULAR VAULT\\\", \\\"G-UNI\\\", \\\"RWA\\\", \\\"PSM\\\"], \\\"y\\\": [4529137859.491507, 167957979.70324078, null, 3363958622.2020836]}, {\\\"hovertemplate\\\": \\\"%{y:,.2f}<extra></extra>\\\", \\\"marker\\\": {\\\"color\\\": \\\"#1aab9b\\\"}, \\\"name\\\": \\\"Debt (DAI)\\\", \\\"type\\\": \\\"bar\\\", \\\"x\\\": [\\\"REGULAR VAULT\\\", \\\"G-UNI\\\", \\\"RWA\\\", \\\"PSM\\\"], \\\"y\\\": [1038295651.1635101, 163982435.5552121, 702837569.4415212, 3363958622.2020836]}], \\\"layout\\\": {\\\"barmode\\\": \\\"group\\\", \\\"hovermode\\\": \\\"x unified\\\", \\\"paper_bgcolor\\\": \\\"#fcfcfc\\\", \\\"plot_bgcolor\\\": \\\"#fcfcfc\\\", \\\"template\\\": {\\\"data\\\": {\\\"bar\\\": [{\\\"error_x\\\": {\\\"color\\\": \\\"#2a3f5f\\\"}, \\\"error_y\\\": {\\\"color\\\": \\\"#2a3f5f\\\"}, \\\"marker\\\": {\\\"line\\\": {\\\"color\\\": \\\"#E5ECF6\\\", \\\"width\\\": 0.5}}, \\\"type\\\": \\\"bar\\\"}], \\\"barpolar\\\": [{\\\"marker\\\": {\\\"line\\\": {\\\"color\\\": \\\"#E5ECF6\\\", \\\"width\\\": 0.5}}, \\\"type\\\": \\\"barpolar\\\"}], \\\"carpet\\\": [{\\\"aaxis\\\": {\\\"endlinecolor\\\": \\\"#2a3f5f\\\", \\\"gridcolor\\\": \\\"white\\\", \\\"linecolor\\\": \\\"white\\\", \\\"minorgridcolor\\\": \\\"white\\\", \\\"startlinecolor\\\": \\\"#2a3f5f\\\"}, \\\"baxis\\\": {\\\"endlinecolor\\\": \\\"#2a3f5f\\\", \\\"gridcolor\\\": \\\"white\\\", \\\"linecolor\\\": \\\"white\\\", \\\"minorgridcolor\\\": \\\"white\\\", \\\"startlinecolor\\\": \\\"#2a3f5f\\\"}, \\\"type\\\": \\\"carpet\\\"}], \\\"choropleth\\\": [{\\\"colorbar\\\": {\\\"outlinewidth\\\": 0, \\\"ticks\\\": \\\"\\\"}, \\\"type\\\": \\\"choropleth\\\"}], \\\"contour\\\": [{\\\"colorbar\\\": {\\\"outlinewidth\\\": 0, \\\"ticks\\\": \\\"\\\"}, \\\"colorscale\\\": [[0, \\\"#0d0887\\\"], [0.1111111111111111, \\\"#46039f\\\"], [0.2222222222222222, \\\"#7201a8\\\"], [0.3333333333333333, \\\"#9c179e\\\"], [0.4444444444444444, \\\"#bd3786\\\"], [0.5555555555555556, \\\"#d8576b\\\"], [0.6666666666666666, \\\"#ed7953\\\"], [0.7777777777777778, \\\"#fb9f3a\\\"], [0.8888888888888888, \\\"#fdca26\\\"], [1, \\\"#f0f921\\\"]], \\\"type\\\": \\\"contour\\\"}], \\\"contourcarpet\\\": [{\\\"colorbar\\\": {\\\"outlinewidth\\\": 0, \\\"ticks\\\": \\\"\\\"}, \\\"type\\\": \\\"contourcarpet\\\"}], \\\"heatmap\\\": [{\\\"colorbar\\\": {\\\"outlinewidth\\\": 0, \\\"ticks\\\": \\\"\\\"}, \\\"colorscale\\\": [[0, \\\"#0d0887\\\"], [0.1111111111111111, \\\"#46039f\\\"], [0.2222222222222222, \\\"#7201a8\\\"], [0.3333333333333333, \\\"#9c179e\\\"], [0.4444444444444444, \\\"#bd3786\\\"], [0.5555555555555556, \\\"#d8576b\\\"], [0.6666666666666666, \\\"#ed7953\\\"], [0.7777777777777778, \\\"#fb9f3a\\\"], [0.8888888888888888, \\\"#fdca26\\\"], [1, \\\"#f0f921\\\"]], \\\"type\\\": \\\"heatmap\\\"}], \\\"heatmapgl\\\": [{\\\"colorbar\\\": {\\\"outlinewidth\\\": 0, \\\"ticks\\\": \\\"\\\"}, \\\"colorscale\\\": [[0, \\\"#0d0887\\\"], [0.1111111111111111, \\\"#46039f\\\"], [0.2222222222222222, \\\"#7201a8\\\"], [0.3333333333333333, \\\"#9c179e\\\"], [0.4444444444444444, \\\"#bd3786\\\"], [0.5555555555555556, \\\"#d8576b\\\"], [0.6666666666666666, \\\"#ed7953\\\"], [0.7777777777777778, \\\"#fb9f3a\\\"], [0.8888888888888888, \\\"#fdca26\\\"], [1, \\\"#f0f921\\\"]], \\\"type\\\": \\\"heatmapgl\\\"}], \\\"histogram\\\": [{\\\"marker\\\": {\\\"colorbar\\\": {\\\"outlinewidth\\\": 0, \\\"ticks\\\": \\\"\\\"}}, \\\"type\\\": \\\"histogram\\\"}], \\\"histogram2d\\\": [{\\\"colorbar\\\": {\\\"outlinewidth\\\": 0, \\\"ticks\\\": \\\"\\\"}, \\\"colorscale\\\": [[0, \\\"#0d0887\\\"], [0.1111111111111111, \\\"#46039f\\\"], [0.2222222222222222, \\\"#7201a8\\\"], [0.3333333333333333, \\\"#9c179e\\\"], [0.4444444444444444, \\\"#bd3786\\\"], [0.5555555555555556, \\\"#d8576b\\\"], [0.6666666666666666, \\\"#ed7953\\\"], [0.7777777777777778, \\\"#fb9f3a\\\"], [0.8888888888888888, \\\"#fdca26\\\"], [1, \\\"#f0f921\\\"]], \\\"type\\\": \\\"histogram2d\\\"}], \\\"histogram2dcontour\\\": [{\\\"colorbar\\\": {\\\"outlinewidth\\\": 0, \\\"ticks\\\": \\\"\\\"}, \\\"colorscale\\\": [[0, \\\"#0d0887\\\"], [0.1111111111111111, \\\"#46039f\\\"], [0.2222222222222222, \\\"#7201a8\\\"], [0.3333333333333333, \\\"#9c179e\\\"], [0.4444444444444444, \\\"#bd3786\\\"], [0.5555555555555556, \\\"#d8576b\\\"], [0.6666666666666666, \\\"#ed7953\\\"], [0.7777777777777778, \\\"#fb9f3a\\\"], [0.8888888888888888, \\\"#fdca26\\\"], [1, \\\"#f0f921\\\"]], \\\"type\\\": \\\"histogram2dcontour\\\"}], \\\"mesh3d\\\": [{\\\"colorbar\\\": {\\\"outlinewidth\\\": 0, \\\"ticks\\\": \\\"\\\"}, \\\"type\\\": \\\"mesh3d\\\"}], \\\"parcoords\\\": [{\\\"line\\\": {\\\"colorbar\\\": {\\\"outlinewidth\\\": 0, \\\"ticks\\\": \\\"\\\"}}, \\\"type\\\": \\\"parcoords\\\"}], \\\"pie\\\": [{\\\"automargin\\\": true, \\\"type\\\": \\\"pie\\\"}], \\\"scatter\\\": [{\\\"marker\\\": {\\\"colorbar\\\": {\\\"outlinewidth\\\": 0, \\\"ticks\\\": \\\"\\\"}}, \\\"type\\\": \\\"scatter\\\"}], \\\"scatter3d\\\": [{\\\"line\\\": {\\\"colorbar\\\": {\\\"outlinewidth\\\": 0, \\\"ticks\\\": \\\"\\\"}}, \\\"marker\\\": {\\\"colorbar\\\": {\\\"outlinewidth\\\": 0, \\\"ticks\\\": \\\"\\\"}}, \\\"type\\\": \\\"scatter3d\\\"}], \\\"scattercarpet\\\": [{\\\"marker\\\": {\\\"colorbar\\\": {\\\"outlinewidth\\\": 0, \\\"ticks\\\": \\\"\\\"}}, \\\"type\\\": \\\"scattercarpet\\\"}], \\\"scattergeo\\\": [{\\\"marker\\\": {\\\"colorbar\\\": {\\\"outlinewidth\\\": 0, \\\"ticks\\\": \\\"\\\"}}, \\\"type\\\": \\\"scattergeo\\\"}], \\\"scattergl\\\": [{\\\"marker\\\": {\\\"colorbar\\\": {\\\"outlinewidth\\\": 0, \\\"ticks\\\": \\\"\\\"}}, \\\"type\\\": \\\"scattergl\\\"}], \\\"scattermapbox\\\": [{\\\"marker\\\": {\\\"colorbar\\\": {\\\"outlinewidth\\\": 0, \\\"ticks\\\": \\\"\\\"}}, \\\"type\\\": \\\"scattermapbox\\\"}], \\\"scatterpolar\\\": [{\\\"marker\\\": {\\\"colorbar\\\": {\\\"outlinewidth\\\": 0, \\\"ticks\\\": \\\"\\\"}}, \\\"type\\\": \\\"scatterpolar\\\"}], \\\"scatterpolargl\\\": [{\\\"marker\\\": {\\\"colorbar\\\": {\\\"outlinewidth\\\": 0, \\\"ticks\\\": \\\"\\\"}}, \\\"type\\\": \\\"scatterpolargl\\\"}], \\\"scatterternary\\\": [{\\\"marker\\\": {\\\"colorbar\\\": {\\\"outlinewidth\\\": 0, \\\"ticks\\\": \\\"\\\"}}, \\\"type\\\": \\\"scatterternary\\\"}], \\\"surface\\\": [{\\\"colorbar\\\": {\\\"outlinewidth\\\": 0, \\\"ticks\\\": \\\"\\\"}, \\\"colorscale\\\": [[0, \\\"#0d0887\\\"], [0.1111111111111111, \\\"#46039f\\\"], [0.2222222222222222, \\\"#7201a8\\\"], [0.3333333333333333, \\\"#9c179e\\\"], [0.4444444444444444, \\\"#bd3786\\\"], [0.5555555555555556, \\\"#d8576b\\\"], [0.6666666666666666, \\\"#ed7953\\\"], [0.7777777777777778, \\\"#fb9f3a\\\"], [0.8888888888888888, \\\"#fdca26\\\"], [1, \\\"#f0f921\\\"]], \\\"type\\\": \\\"surface\\\"}], \\\"table\\\": [{\\\"cells\\\": {\\\"fill\\\": {\\\"color\\\": \\\"#EBF0F8\\\"}, \\\"line\\\": {\\\"color\\\": \\\"white\\\"}}, \\\"header\\\": {\\\"fill\\\": {\\\"color\\\": \\\"#C8D4E3\\\"}, \\\"line\\\": {\\\"color\\\": \\\"white\\\"}}, \\\"type\\\": \\\"table\\\"}]}, \\\"layout\\\": {\\\"annotationdefaults\\\": {\\\"arrowcolor\\\": \\\"#2a3f5f\\\", \\\"arrowhead\\\": 0, \\\"arrowwidth\\\": 1}, \\\"coloraxis\\\": {\\\"colorbar\\\": {\\\"outlinewidth\\\": 0, \\\"ticks\\\": \\\"\\\"}}, \\\"colorscale\\\": {\\\"diverging\\\": [[0, \\\"#8e0152\\\"], [0.1, \\\"#c51b7d\\\"], [0.2, \\\"#de77ae\\\"], [0.3, \\\"#f1b6da\\\"], [0.4, \\\"#fde0ef\\\"], [0.5, \\\"#f7f7f7\\\"], [0.6, \\\"#e6f5d0\\\"], [0.7, \\\"#b8e186\\\"], [0.8, \\\"#7fbc41\\\"], [0.9, \\\"#4d9221\\\"], [1, \\\"#276419\\\"]], \\\"sequential\\\": [[0, \\\"#0d0887\\\"], [0.1111111111111111, \\\"#46039f\\\"], [0.2222222222222222, \\\"#7201a8\\\"], [0.3333333333333333, \\\"#9c179e\\\"], [0.4444444444444444, \\\"#bd3786\\\"], [0.5555555555555556, \\\"#d8576b\\\"], [0.6666666666666666, \\\"#ed7953\\\"], [0.7777777777777778, \\\"#fb9f3a\\\"], [0.8888888888888888, \\\"#fdca26\\\"], [1, \\\"#f0f921\\\"]], \\\"sequentialminus\\\": [[0, \\\"#0d0887\\\"], [0.1111111111111111, \\\"#46039f\\\"], [0.2222222222222222, \\\"#7201a8\\\"], [0.3333333333333333, \\\"#9c179e\\\"], [0.4444444444444444, \\\"#bd3786\\\"], [0.5555555555555556, \\\"#d8576b\\\"], [0.6666666666666666, \\\"#ed7953\\\"], [0.7777777777777778, \\\"#fb9f3a\\\"], [0.8888888888888888, \\\"#fdca26\\\"], [1, \\\"#f0f921\\\"]]}, \\\"colorway\\\": [\\\"#636efa\\\", \\\"#EF553B\\\", \\\"#00cc96\\\", \\\"#ab63fa\\\", \\\"#FFA15A\\\", \\\"#19d3f3\\\", \\\"#FF6692\\\", \\\"#B6E880\\\", \\\"#FF97FF\\\", \\\"#FECB52\\\"], \\\"font\\\": {\\\"color\\\": \\\"#2a3f5f\\\"}, \\\"geo\\\": {\\\"bgcolor\\\": \\\"white\\\", \\\"lakecolor\\\": \\\"white\\\", \\\"landcolor\\\": \\\"#E5ECF6\\\", \\\"showlakes\\\": true, \\\"showland\\\": true, \\\"subunitcolor\\\": \\\"white\\\"}, \\\"hoverlabel\\\": {\\\"align\\\": \\\"left\\\"}, \\\"hovermode\\\": \\\"closest\\\", \\\"mapbox\\\": {\\\"style\\\": \\\"light\\\"}, \\\"paper_bgcolor\\\": \\\"white\\\", \\\"plot_bgcolor\\\": \\\"#E5ECF6\\\", \\\"polar\\\": {\\\"angularaxis\\\": {\\\"gridcolor\\\": \\\"white\\\", \\\"linecolor\\\": \\\"white\\\", \\\"ticks\\\": \\\"\\\"}, \\\"bgcolor\\\": \\\"#E5ECF6\\\", \\\"radialaxis\\\": {\\\"gridcolor\\\": \\\"white\\\", \\\"linecolor\\\": \\\"white\\\", \\\"ticks\\\": \\\"\\\"}}, \\\"scene\\\": {\\\"xaxis\\\": {\\\"backgroundcolor\\\": \\\"#E5ECF6\\\", \\\"gridcolor\\\": \\\"white\\\", \\\"gridwidth\\\": 2, \\\"linecolor\\\": \\\"white\\\", \\\"showbackground\\\": true, \\\"ticks\\\": \\\"\\\", \\\"zerolinecolor\\\": \\\"white\\\"}, \\\"yaxis\\\": {\\\"backgroundcolor\\\": \\\"#E5ECF6\\\", \\\"gridcolor\\\": \\\"white\\\", \\\"gridwidth\\\": 2, \\\"linecolor\\\": \\\"white\\\", \\\"showbackground\\\": true, \\\"ticks\\\": \\\"\\\", \\\"zerolinecolor\\\": \\\"white\\\"}, \\\"zaxis\\\": {\\\"backgroundcolor\\\": \\\"#E5ECF6\\\", \\\"gridcolor\\\": \\\"white\\\", \\\"gridwidth\\\": 2, \\\"linecolor\\\": \\\"white\\\", \\\"showbackground\\\": true, \\\"ticks\\\": \\\"\\\", \\\"zerolinecolor\\\": \\\"white\\\"}}, \\\"shapedefaults\\\": {\\\"line\\\": {\\\"color\\\": \\\"#2a3f5f\\\"}}, \\\"ternary\\\": {\\\"aaxis\\\": {\\\"gridcolor\\\": \\\"white\\\", \\\"linecolor\\\": \\\"white\\\", \\\"ticks\\\": \\\"\\\"}, \\\"baxis\\\": {\\\"gridcolor\\\": \\\"white\\\", \\\"linecolor\\\": \\\"white\\\", \\\"ticks\\\": \\\"\\\"}, \\\"bgcolor\\\": \\\"#E5ECF6\\\", \\\"caxis\\\": {\\\"gridcolor\\\": \\\"white\\\", \\\"linecolor\\\": \\\"white\\\", \\\"ticks\\\": \\\"\\\"}}, \\\"title\\\": {\\\"x\\\": 0.05}, \\\"xaxis\\\": {\\\"automargin\\\": true, \\\"gridcolor\\\": \\\"white\\\", \\\"linecolor\\\": \\\"white\\\", \\\"ticks\\\": \\\"\\\", \\\"title\\\": {\\\"standoff\\\": 15}, \\\"zerolinecolor\\\": \\\"white\\\", \\\"zerolinewidth\\\": 2}, \\\"yaxis\\\": {\\\"automargin\\\": true, \\\"gridcolor\\\": \\\"white\\\", \\\"linecolor\\\": \\\"white\\\", \\\"ticks\\\": \\\"\\\", \\\"title\\\": {\\\"standoff\\\": 15}, \\\"zerolinecolor\\\": \\\"white\\\", \\\"zerolinewidth\\\": 2}}}, \\\"title\\\": {\\\"text\\\": \\\"Value locked (USD) & debt (DAI) split by vault type\\\", \\\"x\\\": 0.5, \\\"xanchor\\\": \\\"center\\\"}, \\\"xaxis\\\": {\\\"tickangle\\\": -45}}}\"\n  }\n}\n"}]